jinsup_fast_ml/__init__.py
jinsup_fast_ml/core.py
jinsup_fast_ml/global_device.py
jinsup_fast_ml-0.1.7.dist-info/METADATA
jinsup_fast_ml-0.1.7.dist-info/WHEEL
jinsup_fast_ml-0.1.7.dist-info/top_level.txt
jinsup_fast_ml-0.1.7.dist-info/RECORD
