Metadata-Version: 2.4
Name: jinsup-fast-ml
Version: 0.1.7
Summary: Wanted AI Agent - Jinsup Fast ML
Author-email: Seobi <dlwlstjq410@gmail.com>
License: MIT
Requires-Python: >=3.10
Requires-Dist: lazypredict>=0.2.16
Requires-Dist: lightgbm>=4.6.0
Requires-Dist: optuna>=4.4.0
Requires-Dist: torch>=2.7.1
Requires-Dist: xgboost>=3.0.4
